Metadata-Version: 2.1
Name: AudioStudio
Version: 0.0.3
Summary: A library for working with audio data
Home-page: https://github.com/danrabayda/AudioStudio
Author: Daniel Rabayda
Author-email: rabaydadp@gmail.com
License: MIT
Platform: UNKNOWN
License-File: LICENSE.txt
